argon2_hasher-0.1.3.dist-info/METADATA
argon2_hasher-0.1.3.dist-info/WHEEL
argon2_hasher-0.1.3.dist-info/licenses/LICENSE
argon2_hasher/__init__.py
argon2_hasher/__pycache__/__init__.cpython-311.pyc
argon2_hasher/argon2_hasher.cpython-311-aarch64-linux-gnu.so
argon2_hasher/argon2_hasher.pyi
argon2_hasher-0.1.3.dist-info/RECORD
