Metadata-Version: 2.4
Name: argon2-hasher
Version: 0.1.3
Classifier: Programming Language :: Python :: 3
Classifier: Programming Language :: Rust
Classifier: License :: OSI Approved :: MIT License
Classifier: Operating System :: OS Independent
License-File: LICENSE
Summary: A Python-wrapped Rust Argon2 Hasher
Keywords: argon2,password,hash,rust,pyo3
Author: Malaa Technologies <engineering@malaa.tech>
Author-email: Malaa Technologies <engineering@malaa.tech>
License: MIT
Project-URL: Source Code, https://github.com/malaa-tech/argon2-hasher
